gkvfig/__init__.py
gkvfig/__main__.py
gkvfig/make_pdf.py
gkvfig/utils/__init__.py
gkvfig/utils/build_text_section.py
gkvfig/utils/calc_elt.py
gkvfig/utils/calc_entropy_balance.py
gkvfig/utils/parse_parameter_setting.py
gkvfig/utils/plot_elt.py
gkvfig/utils/plot_energy.py
gkvfig/utils/plot_flux.py
gkvfig/utils/plot_freq.py
gkvfig/utils/plot_mtrf.py
gkvfig/utils/plot_time_series.py
gkvfig-0.1.1.dist-info/licenses/LICENSE
gkvfig-0.1.1.dist-info/METADATA
gkvfig-0.1.1.dist-info/WHEEL
gkvfig-0.1.1.dist-info/top_level.txt
gkvfig-0.1.1.dist-info/RECORD
