Metadata-Version: 2.4
Name: gkvfig
Version: 0.1.1
Summary: A Python package for generating PDF of GKV standard ASCII output
Author-email: Shinya Maeyama <maeyama.shinya@nifs.ac.jp>
License: MIT License
Requires-Python: >=3.7
License-File: LICENSE
Requires-Dist: numpy>=1.24
Requires-Dist: matplotlib>=3.8
Requires-Dist: pandas>=2.2
Requires-Dist: reportlab>=4.0
Requires-Dist: pypdf>=4.3
Dynamic: license-file
